LayerNet.py
layernet-0.0.5.dist-info/METADATA
layernet-0.0.5.dist-info/WHEEL
layernet-0.0.5.dist-info/top_level.txt
layernet-0.0.5.dist-info/RECORD
