Metadata-Version: 2.4
Name: layernet
Version: 0.0.5
Summary: Biblioteca modular de Machine Learning em um único arquivo, inspirada em Keras/TensorFlow.
Author: Leonardo Nery
Author-email: leonardonery@gmail.com
Keywords: machine-learning deep-learning keras tensorflow neural-networks ai
Classifier: Programming Language :: Python :: 3
Classifier: License :: OSI Approved :: MIT License
Classifier: Operating System :: OS Independent
Classifier: Intended Audience :: Science/Research
Classifier: Topic :: Scientific/Engineering :: Artificial Intelligence
Requires-Python: >=3.8
Requires-Dist: tensorflow>=2.9.0
Requires-Dist: keras>=2.9.0
Requires-Dist: numpy
Requires-Dist: matplotlib
Requires-Dist: pandas
Requires-Dist: networkx
Requires-Dist: sympy
Requires-Dist: pyqt5
Dynamic: author
Dynamic: author-email
Dynamic: classifier
Dynamic: description
Dynamic: description-content-type
Dynamic: keywords
Dynamic: requires-dist
Dynamic: requires-python
Dynamic: summary
